fortifyapi/__init__.py
fortifyapi/api.py
fortifyapi/client.py
fortifyapi/exceptions.py
fortifyapi/fortify.py
fortifyapi/query.py
fortifyapi/template.py
fortifyapi-3.1.25.dist-info/LICENSE
fortifyapi-3.1.25.dist-info/METADATA
fortifyapi-3.1.25.dist-info/WHEEL
fortifyapi-3.1.25.dist-info/top_level.txt
fortifyapi-3.1.25.dist-info/zip-safe
fortifyapi-3.1.25.dist-info/RECORD
