Metadata-Version: 2.1
Name: fortifyapi
Version: 3.1.25
Summary: Python library for Fortify Software Security Center (SSC) RESTFul API
Home-page: https://github.com/fortifyadmin/fortifyapi
Download-URL: https://github.com/fortifyadmin/fortifyapi/tarball/3.1.25
Author: Brandon Spruth, Matthew Gill
Author-email: brandon@spruth.co, mgill@c0ffee.me
License: MIT
Keywords: fortify,api,security,software,microfocus,ssc,sast
Classifier: Development Status :: 4 - Beta
Classifier: Intended Audience :: Developers
Classifier: Natural Language :: English
Classifier: License :: OSI Approved :: MIT License
Classifier: Topic :: Software Development
Classifier: Topic :: Software Development :: Libraries :: Python Modules
Classifier: Topic :: Software Development :: Libraries :: Application Frameworks
Classifier: Operating System :: OS Independent
Classifier: Programming Language :: Python :: 3
Classifier: Programming Language :: Python :: 3.6
Classifier: Programming Language :: Python :: 3.7
Classifier: Programming Language :: Python :: 3.8
License-File: LICENSE
Requires-Dist: requests
Requires-Dist: requests-toolbelt
